vfastpunct/__init__.py
vfastpunct/constants.py
vfastpunct/log.py
vfastpunct/predictor.py
vfastpunct/processor.py
vfastpunct/ultis.py
vfastpunct/models/__init__.py
vfastpunct/models/base_model.py
vfastpunct/models/punct_bert.py
vfastpunct/models/punct_cap_bert.py
vfastpunct/models/punct_cap_lstm.py
vfastpunct/models/punct_lstm.py
VFastPunct-2.0.2.dist-info/METADATA
VFastPunct-2.0.2.dist-info/WHEEL
VFastPunct-2.0.2.dist-info/top_level.txt
VFastPunct-2.0.2.dist-info/RECORD
