Metadata-Version: 2.1
Name: VFastPunct
Version: 2.0.2
Summary: Fast Punctuation Restoration for Vietnamese
Home-page: https://github.com/Hung-Thinh-Innovation/vfastPunct
Author: DatNgo
Author-email: datnnt97@gmail.com
License: MIT
Platform: UNKNOWN
Classifier: License :: OSI Approved :: MIT License
Classifier: Programming Language :: Python :: 3
Classifier: Programming Language :: Python :: 3.8
Requires-Dist: torch (>1.8.2)
Requires-Dist: transformers
Requires-Dist: pytorch-crf (~=0.7.2)
